setup.py
bin/aimes-skeleton-generate
bin/aimes-skeleton-version
bin/dax2dot
src/aimes/__init__.py
src/aimes.skeleton.egg-info/PKG-INFO
src/aimes.skeleton.egg-info/SOURCES.txt
src/aimes.skeleton.egg-info/dependency_links.txt
src/aimes.skeleton.egg-info/namespace_packages.txt
src/aimes.skeleton.egg-info/not-zip-safe
src/aimes.skeleton.egg-info/top_level.txt
src/aimes/skeleton/VERSION
src/aimes/skeleton/VERSION.git
src/aimes/skeleton/__init__.py
src/aimes/skeleton/skeleton_api.py
src/aimes/skeleton/skeleton_impl.py
src/aimes/skeleton/task.c
src/aimes/skeleton/../../../VERSION
src/aimes/skeleton/Pegasus/DAX3.py
src/aimes/skeleton/Pegasus/__init__.py